Metadata-Version: 1.0
Name: pagure-dist-git
Version: 0.6
Summary: Pagure gitolite plugin for Fedora's dist-git setup.
Home-page: https://pagure.io/pagure-dist-git
Author: Pierre-Yves Chibon
Author-email: pingou@fedoraproject.org
License: GPLv2+
Platform: UNKNOWN
